boguan_yuequ/__init__.py
boguan_yuequ/_modidx.py
boguan_yuequ/core.py
boguan_yuequ/algorithms/__init__.py
boguan_yuequ/algorithms/wave_high/__init__.py
boguan_yuequ/algorithms/wave_high/modeling_wave_high.py
博观约取/__init__.py
BoGuan_YueQu-0.0.2.dist-info/LICENSE
BoGuan_YueQu-0.0.2.dist-info/METADATA
BoGuan_YueQu-0.0.2.dist-info/WHEEL
BoGuan_YueQu-0.0.2.dist-info/entry_points.txt
BoGuan_YueQu-0.0.2.dist-info/top_level.txt
BoGuan_YueQu-0.0.2.dist-info/RECORD
