Metadata-Version: 2.1
Name: BoGuan_YueQu
Version: 0.0.2
Summary: BoGuan_YueQu: Streamline Your Large Vision Models with SOTA Parameter-Efficient Fine-Tuning (a.k.a. Delta Tuning) Algorithms 博观而约取——一个优雅的参数高效微调（增量微调）库
Home-page: https://github.com/THU-CVML/BoGuan_YueQu
Author: 叶璨铭
Author-email: 12011404@mail.sustech.edu.cn
License: Apache Software License 2.0
Keywords: nbdev jupyter notebook python
Classifier: Development Status :: 4 - Beta
Classifier: Intended Audience :: Developers
Classifier: Natural Language :: English
Classifier: Programming Language :: Python :: 3.7
Classifier: Programming Language :: Python :: 3.8
Classifier: Programming Language :: Python :: 3.9
Classifier: Programming Language :: Python :: 3.10
Classifier: License :: OSI Approved :: Apache Software License
Requires-Python: >=3.7
License-File: LICENSE
Provides-Extra: dev
